graphreport_metrics/Make_new.py
graphreport_metrics/__init__.py
graphreport_metrics/graphreport.py
graphreport_metrics/keyword_results.py
graphreport_metrics/keyword_stats.py
graphreport_metrics/runner.py
graphreport_metrics/suite_results.py
graphreport_metrics/test_results.py
graphreport_metrics/test_stats.py
graphreport_metrics/version.py
graphreport-1.2.3.dist-info/LICENSE
graphreport-1.2.3.dist-info/METADATA
graphreport-1.2.3.dist-info/WHEEL
graphreport-1.2.3.dist-info/entry_points.txt
graphreport-1.2.3.dist-info/top_level.txt
graphreport-1.2.3.dist-info/zip-safe
graphreport-1.2.3.dist-info/RECORD
