Metadata-Version: 2.1
Name: graphreport
Version: 1.2.3
Summary: Custom metrics based report for robot framework
Home-page: https://github.com/usr123321/graphreport
Author: user
Author-email: mdeepakm69@gmail.com
License: UNKNOWN
Keywords: Robot framework graphreport
Platform: UNKNOWN
Classifier: Framework :: Robot Framework
Classifier: Programming Language :: Python
Classifier: Topic :: Software Development :: Testing
Requires-Dist: robotframework
Requires-Dist: beautifulsoup4
Requires-Dist: gevent
